LICENSE
README.md
setup.py
datapanel/__init__.py
datapanel/core.py
datapanel.egg-info/PKG-INFO
datapanel.egg-info/SOURCES.txt
datapanel.egg-info/dependency_links.txt
datapanel.egg-info/top_level.txt