Metadata-Version: 2.4
Name: datapanel
Version: 0.0.4
Summary: datapanel.dev downloader
Home-page: 
Author: ning9527
Author-email: lizhi.guo@foxmail.com
Classifier: Programming Language :: Python :: 3
Classifier: License :: OSI Approved :: MIT License
Classifier: Operating System :: OS Independent
Requires-Python: >=3.6
License-File: LICENSE
Dynamic: author
Dynamic: author-email
Dynamic: classifier
Dynamic: description
Dynamic: description-content-type
Dynamic: license-file
Dynamic: requires-python
Dynamic: summary
